odoo/addons/partner_phone_search/README.rst
odoo/addons/partner_phone_search/__init__.py
odoo/addons/partner_phone_search/__manifest__.py
odoo/addons/partner_phone_search/i18n/partner_phone_search.pot
odoo/addons/partner_phone_search/models/__init__.py
odoo/addons/partner_phone_search/models/res_partner.py
odoo/addons/partner_phone_search/static/description/icon.png
odoo/addons/partner_phone_search/tests/__init__.py
odoo/addons/partner_phone_search/tests/test_partner.py
odoo11_addon_partner_phone_search-11.0.1.0.1.dist-info/METADATA
odoo11_addon_partner_phone_search-11.0.1.0.1.dist-info/WHEEL
odoo11_addon_partner_phone_search-11.0.1.0.1.dist-info/top_level.txt
odoo11_addon_partner_phone_search-11.0.1.0.1.dist-info/RECORD
